shfz_flask/__init__.py
shfz_flask/shfztrace.py
shfzflask/__init__.py
shfzflask/shfztrace.py
src/shfz_flask/__init__.py
src/shfz_flask/shfztrace.py
shfzflask-0.0.2.dist-info/LICENSE
shfzflask-0.0.2.dist-info/METADATA
shfzflask-0.0.2.dist-info/WHEEL
shfzflask-0.0.2.dist-info/top_level.txt
shfzflask-0.0.2.dist-info/RECORD
