Metadata-Version: 2.1
Name: shfzflask
Version: 0.0.2
Summary: Scenario-based fuzzing test's trace library
Home-page: https://github.com/shfz/shfz-flask
Author: hi120ki
Author-email: hi120ki@outlook.jp
License: MIT
Platform: UNKNOWN
Requires-Dist: flask
